resynthesizer/__init__.py
resynthesizer/resynthesizer.py
resynthesizer/bin/libresynthesizer.dll
resynthesizer/bin/libresynthesizer.so
resynthesizer/bin/libresynthesizer_universal.dylib
resynthesizer-1.2.dist-info/METADATA
resynthesizer-1.2.dist-info/WHEEL
resynthesizer-1.2.dist-info/top_level.txt
resynthesizer-1.2.dist-info/RECORD
