Metadata-Version: 2.1
Name: resynthesizer
Version: 1.2
Summary: A very old open-source "Content-Aware Fill" method
Home-page: https://github.com/light-and-ray/resynthesizer-python-lib
License: GPL-3.0
Platform: UNKNOWN
